{
  "date": "2026-03-30",
  "fetchedAt": "2026-03-31T00:00:20.499Z",
  "ratings": {
    "merriment-social": { "rating": 4.4, "totalRatings": 889, "trend": "stable" },
    "third-coast": { "rating": 4.5, "totalRatings": 503, "trend": "stable" },
    "flourchild": { "rating": 4.5, "totalRatings": 291, "trend": "stable" },
    "loon-room": { "rating": 4.7, "totalRatings": 35, "trend": "stable" }
  },
  "alerts": [
    {
      "entity": "third-coast",
      "platform": "google",
      "author": "Korinne Mack",
      "rating": 2,
      "sentiment": "negative",
      "issues": ["food quality (too salty)", "service (ignored as solo diner for 45 min)"],
      "needs_response": true
    },
    {
      "entity": "flourchild",
      "platform": "google",
      "author": "Jim Whitaker",
      "rating": 2,
      "sentiment": "negative",
      "issues": ["pizza quality (dry crust, bland sauce)", "value for price"],
      "needs_response": true
    }
  ],
  "changes_from_previous": {
    "flourchild_total_ratings": "290 → 291 (+1 new review)"
  },
  "review_sentiment_breakdown": {
    "merriment-social": { "positive": 4, "neutral": 0, "mixed": 1, "negative": 0 },
    "third-coast": { "positive": 3, "neutral": 0, "mixed": 1, "negative": 1 },
    "flourchild": { "positive": 4, "neutral": 0, "mixed": 0, "negative": 1 },
    "loon-room": { "positive": 4, "neutral": 0, "mixed": 1, "negative": 0 }
  }
}
